{
  "version": "1.0.0",
  "encrypted": "U2FsdGVkX1+vupppZksvRf5pq5g5XjFRlipRkwB0K1Y96Qsv2Lm+31cmzaAILwytX0lDZvFPuLZtPlmm3kJUZvU3nzLFgTbGmPXLmDvZjQ==",
  "iv": "czNjcjN0X2l2XzEyMzQ1Njc4",
  "authTag": "YXV0aF90YWdfZXhhbXBsZQ==",
  "signature": "ZXhhbXBsZV9zaWduYXR1cmVfaGFzaF92YWx1ZQ==",
  "algorithm": "aes-256-gcm",
  "timestamp": "2025-01-18T00:00:00.000Z",
  "_comment": "This is an example encrypted configuration. The actual encrypted data is not decryptable without the proper encryption key."
}
